hcam_devices/__init__.py
hcam_devices/components/__init__.py
hcam_devices/devices/__init__.py
hcam_devices/devices/honeywell.py
hcam_devices/devices/meerstetter.py
hcam_devices/devices/newport.py
hcam_devices/devices/ngc.py
hcam_devices/devices/pdr900.py
hcam_devices/devices/properties.py
hcam_devices/devices/unichiller.py
hcam_devices/devices/zaber.py
hcam_devices/gtc/corba.py
hcam_devices/gtc/headers.py
hcam_devices/machines/__init__.py
hcam_devices/machines/connections.yaml
hcam_devices/machines/controller.yaml
hcam_devices/machines/gtc.yaml
hcam_devices/machines/motors.yaml
hcam_devices/machines/sensor.yaml
hcam_devices/models/__init__.py
hcam_devices/models/ccd.py
hcam_devices/models/compo.py
hcam_devices/models/flow_sensor.py
hcam_devices/models/gps.py
hcam_devices/models/gtc_cooling.py
hcam_devices/models/meerstetter.py
hcam_devices/models/ngc.py
hcam_devices/models/rack.py
hcam_devices/models/rackpc.py
hcam_devices/models/slide.py
hcam_devices/models/telescope.py
hcam_devices/models/vac_gauge.py
hcam_devices/testing/__init__.py
hcam_devices/testing/axis.py
hcam_devices/testing/fakeserial.py
hcam_devices/testing/properties.py
hcam_devices/testing/sensors.py
hcam_devices/utils/__init__.py
hcam_devices/utils/filesystem.py
hcam_devices/utils/obsmodes.py
hcam_devices/wamp/__init__.py
hcam_devices/wamp/utils/__init__.py
hcam_devices-1.6.1.data/scripts/do_wamp_call
hcam_devices-1.6.1.data/scripts/gtc_archive_ingest
hcam_devices-1.6.1.data/scripts/gtcserver
hcam_devices-1.6.1.data/scripts/hserver
hcam_devices-1.6.1.data/scripts/hwlogger
hcam_devices-1.6.1.data/scripts/hwserver
hcam_devices-1.6.1.data/scripts/make_diagrams.py
hcam_devices-1.6.1.data/scripts/publish_wamp_msg
hcam_devices-1.6.1.data/scripts/show_telemetry
hcam_devices-1.6.1.data/scripts/tcp_serial_bridge
hcam_devices-1.6.1.data/scripts/zaber_ascii
hcam_devices-1.6.1.dist-info/AUTHORS.rst
hcam_devices-1.6.1.dist-info/LICENSE
hcam_devices-1.6.1.dist-info/METADATA
hcam_devices-1.6.1.dist-info/WHEEL
hcam_devices-1.6.1.dist-info/top_level.txt
hcam_devices-1.6.1.dist-info/RECORD
