Metadata-Version: 2.1
Name: hcam-devices
Version: 1.6.1
Summary: Device Communication via WAMP for HiPerCAM
Home-page: https://github.com/HiPERCAM/hcam_devices
Download-URL: https://github.com/HiPERCAM/hcam_devices/archive/v1.6.1.tar.gz
Author: Stuart Littlefair
Author-email: s.littlefair@shef.ac.uk
License: MIT license
Keywords: hcam_devices
Classifier: Development Status :: 2 - Pre-Alpha
Classifier: Intended Audience :: Developers
Classifier: License :: OSI Approved :: MIT License
Classifier: Natural Language :: English
Classifier: Programming Language :: Python :: 2
Classifier: Programming Language :: Python :: 2.6
Classifier: Programming Language :: Python :: 2.7
Classifier: Programming Language :: Python :: 3
Classifier: Programming Language :: Python :: 3.3
Classifier: Programming Language :: Python :: 3.4
Classifier: Programming Language :: Python :: 3.5
License-File: LICENSE
License-File: AUTHORS.rst
Requires-Dist: astropy
Requires-Dist: requests
Requires-Dist: sismic
Requires-Dist: autobahn
Requires-Dist: pyserial
Requires-Dist: twisted
Requires-Dist: influxdb
Requires-Dist: txaio
Requires-Dist: watchdog
Requires-Dist: six
Requires-Dist: pymodbus3 ; python_version == "3.6"
Requires-Dist: pymodbus ; python_version >= "3.7"
